[
  {
    "acl": [
      {
        "text": "Overview",
        "level": 1,
        "url": "#overview"
      },
      {
        "text": "Creating an ACL",
        "level": 1,
        "url": "#setup"
      },
      {
        "text": "Adding Roles to the ACL",
        "level": 1,
        "url": "#adding-roles"
      },
      {
        "text": "Adding Resources",
        "level": 1,
        "url": "#adding-resources"
      },
      {
        "text": "Defining Access Controls",
        "level": 1,
        "url": "#access-controls"
      },
      {
        "text": "Querying an ACL",
        "level": 1,
        "url": "#querying"
      },
      {
        "text": "Function based access",
        "level": 1,
        "url": "#function-based-access"
      },
      {
        "text": "Objects as role name and resource name",
        "level": 1,
        "url": "#objects"
      },
      {
        "text": "Roles Inheritance",
        "level": 1,
        "url": "#roles-inheritance"
      },
      {
        "text": "Serializing ACL lists",
        "level": 1,
        "url": "#serialization"
      },
      {
        "text": "Events",
        "level": 1,
        "url": "#events"
      },
      {
        "text": "Implementing your own adapters",
        "level": 1,
        "url": "#custom-adapters"
      }
    ]
  },
  {
    "annotations": [
      {
        "text": "Overview",
        "level": 1,
        "url": "#overview"
      },
      {
        "text": "Factory",
        "level": 1,
        "url": "#setup"
      },
      {
        "text": "Adding Roles to the ACL",
        "level": 1,
        "url": "#factory"
      },
      {
        "text": "Reading Annotations",
        "level": 1,
        "url": "#reading"
      },
      {
        "text": "Types of Annotations",
        "level": 1,
        "url": "#types"
      },
      {
        "text": "Practical Usage",
        "level": 1,
        "url": "#usage"
      },
      {
        "text": "Cache Enabler with Annotations",
        "level": 2,
        "url": "#usage-cache"
      },
      {
        "text": "Private/Public areas with Annotations",
        "level": 2,
        "url": "#usage-access-management"
      },
      {
        "text": "Annotations Adapters",
        "level": 1,
        "url": "#adapters"
      },
      {
        "text": "Implementing your own adapters",
        "level": 2,
        "url": "#adapters-custom"
      },
      {
        "text": "External Resources",
        "level": 1,
        "url": "#resources"
      }
    ]
  },
  {
    "application-cli": [
      {
        "text": "Creating a CLI Application",
        "level": 1,
        "url": "#creating-cli-application"
      },
      {
        "text": "Structure",
        "level": 1,
        "url": "#structure"
      },
      {
        "text": "Creating a Bootstrap",
        "level": 1,
        "url": "#creating-bootstrap"
      },
      {
        "text": "Tasks",
        "level": 1,
        "url": "#tasks"
      },
      {
        "text": "Processing action parameters",
        "level": 1,
        "url": "#processing-action-parameters"
      },
      {
        "text": "Running tasks in a chain",
        "level": 1,
        "url": "#running-tasks-chain"
      }
    ]
  },
  {
    "application-micro": [
      {
        "text": "Creating a Micro Application",
        "level": 1,
        "url": "#creating-micro-application"
      },
      {
        "text": "Routing",
        "level": 1,
        "url": "#routing"
      },
      {
        "text": "Setup",
        "level": 2,
        "url": "#routing-setup"
      },
      {
        "text": "Application object",
        "level": 3,
        "url": "#routing-setup-application"
      },
      {
        "text": "Router object",
        "level": 3,
        "url": "#routing-setup-router"
      },
      {
        "text": "Rewrite Rules",
        "level": 2,
        "url": "#rewrite-rules"
      },
      {
        "text": "Handlers",
        "level": 2,
        "url": "#routing-handlers"
      },
      {
        "text": "Definitions",
        "level": 3,
        "url": "#routing-handlers-definitions"
      },
      {
        "text": "Anonymous Function",
        "level": 4,
        "url": "#routing-handlers-anonymous-function"
      },
      {
        "text": "Function",
        "level": 4,
        "url": "#routing-handlers-function"
      },
      {
        "text": "Static Method",
        "level": 4,
        "url": "#routing-handlers-static-method"
      },
      {
        "text": "Method in an Object",
        "level": 4,
        "url": "#routing-handlers-object-method"
      },
      {
        "text": "Controllers",
        "level": 4,
        "url": "#routing-handlers-controllers"
      },
      {
        "text": "Lazy Loading",
        "level": 3,
        "url": "#routing-handlers-controllers-lazy-loading"
      },
      {
        "text": "Use case",
        "level": 4,
        "url": "#routing-handlers-controllers-lazy-loading-use-case"
      },
      {
        "text": "Not Found (404)",
        "level": 3,
        "url": "#routing-handlers-not-found"
      },
      {
        "text": "Methods - Verbs",
        "level": 2,
        "url": "#routing-verbs"
      },
      {
        "text": "delete",
        "level": 3,
        "url": "#routing-verb-delete"
      },
      {
        "text": "get",
        "level": 3,
        "url": "#routing-verb-get"
      },
      {
        "text": "head",
        "level": 3,
        "url": "#routing-verb-head"
      },
      {
        "text": "map",
        "level": 3,
        "url": "#routing-verb-map"
      },
      {
        "text": "options",
        "level": 3,
        "url": "#routing-verb-options"
      },
      {
        "text": "patch",
        "level": 3,
        "url": "#routing-verb-patch"
      },
      {
        "text": "post",
        "level": 3,
        "url": "#routing-verb-post"
      },
      {
        "text": "put",
        "level": 3,
        "url": "#routing-verb-put"
      },
      {
        "text": "Collections",
        "level": 2,
        "url": "#routing-collections"
      },
      {
        "text": "Parameters",
        "level": 2,
        "url": "#routing-parameters"
      },
      {
        "text": "Redirections",
        "level": 2,
        "url": "#routing-redirections"
      },
      {
        "text": "URLs for Routes",
        "level": 2,
        "url": "#routing-urls-for-routes"
      },
      {
        "text": "Dependency Injector",
        "level": 1,
        "url": "#dependency-injector"
      },
      {
        "text": "Responses",
        "level": 1,
        "url": "#responses"
      },
      {
        "text": "Direct output",
        "level": 2,
        "url": "#responses-direct-output"
      },
      {
        "text": "Including another file",
        "level": 2,
        "url": "#responses-include"
      },
      {
        "text": "Direct output JSON",
        "level": 2,
        "url": "#responses-direct-output-json"
      },
      {
        "text": "New Response object",
        "level": 2,
        "url": "#responses-new-response-object"
      },
      {
        "text": "Application Response",
        "level": 2,
        "url": "#responses-application-response"
      },
      {
        "text": "Return Application Response",
        "level": 2,
        "url": "#responses-return-application-response"
      },
      {
        "text": "JSON",
        "level": 2,
        "url": "#responses-json"
      },
      {
        "text": "Events",
        "level": 1,
        "url": "#events"
      },
      {
        "text": "Available events",
        "level": 2,
        "url": "#events-available-events"
      },
      {
        "text": "Authentication example",
        "level": 3,
        "url": "#events-available-events-authentication"
      },
      {
        "text": "Not found example",
        "level": 3,
        "url": "#events-available-events-not-found"
      },
      {
        "text": "Middleware",
        "level": 1,
        "url": ""
      },
      {
        "text": "Attached events",
        "level": 2,
        "url": ""
      },
      {
        "text": "before",
        "level": 3,
        "url": ""
      },
      {
        "text": "after",
        "level": 3,
        "url": ""
      },
      {
        "text": "finish",
        "level": 3,
        "url": ""
      },
      {
        "text": "Implementation",
        "level": 2,
        "url": ""
      },
      {
        "text": "Setup",
        "level": 2,
        "url": ""
      },
      {
        "text": "Events in Middleware",
        "level": 2,
        "url": ""
      },
      {
        "text": "API example",
        "level": 3,
        "url": ""
      },
      {
        "text": "Firewall Middleware",
        "level": 3,
        "url": ""
      },
      {
        "text": "Not Found Middleware",
        "level": 3,
        "url": ""
      },
      {
        "text": "Redirect Middleware",
        "level": 3,
        "url": ""
      },
      {
        "text": "CORS Middleware",
        "level": 3,
        "url": ""
      },
      {
        "text": "Request Middleware",
        "level": 3,
        "url": ""
      },
      {
        "text": "Response Middleware",
        "level": 3,
        "url": ""
      },
      {
        "text": "Models",
        "level": 1,
        "url": ""
      },
      {
        "text": "Injecting Model Instances",
        "level": 1,
        "url": ""
      },
      {
        "text": "Views",
        "level": 1,
        "url": ""
      },
      {
        "text": "Error Handling",
        "level": 1,
        "url": ""
      }
    ]
  },
  {
    "application": [
      {
        "text": "Overview",
        "level": 1,
        "url": "#overview"
      },
      {
        "text": "Manual Bootstrapping",
        "level": 1,
        "url": "#manual-bootstrapping"
      },
      {
        "text": "Single or Multi Module Applications",
        "level": 1,
        "url": "#single-vs-module"
      },
      {
        "text": "Single Module",
        "level": 2,
        "url": "#single"
      },
      {
        "text": "Multi Module",
        "level": 2,
        "url": "#module"
      },
      {
        "text": "Application Events",
        "level": 1,
        "url": "#events"
      },
      {
        "text": "External Resources",
        "level": 1,
        "url": "#resources"
      }
    ]
  },
  {
    "assets": [
      {
        "text": "Overview",
        "level": 1,
        "url": "#overview"
      },
      {
        "text": "Adding Resources",
        "level": 1,
        "url": "#add"
      },
      {
        "text": "Local/Remote resources",
        "level": 1,
        "url": "#resources-local-remote"
      },
      {
        "text": "Collections",
        "level": 1,
        "url": "#collections"
      },
      {
        "text": "URL Prefixes",
        "level": 1,
        "url": "#url-prefixes"
      },
      {
        "text": "Minification/Filtering",
        "level": 1,
        "url": "#minification-filtering"
      },
      {
        "text": "Built-In Filters",
        "level": 2,
        "url": "#builtin-filters"
      },
      {
        "text": "Custom Filters",
        "level": 2,
        "url": "#custom-filters"
      },
      {
        "text": "Custom Output",
        "level": 1,
        "url": ""
      },
      {
        "text": "Improving performance",
        "level": 1,
        "url": ""
      }
    ]
  },
  {
    "cache": [
      {
        "text": "Improving Performance with Cache",
        "level": 1,
        "url": "#overview"
      },
      {
        "text": "When to implement cache?",
        "level": 1,
        "url": "#implementation"
      },
      {
        "text": "Caching Behavior",
        "level": 1,
        "url": "#caching-behavior"
      },
      {
        "text": "Factory",
        "level": 1,
        "url": "#factory"
      },
      {
        "text": "Caching Output Fragments",
        "level": 1,
        "url": "#output-fragments"
      },
      {
        "text": "Caching Arbitrary Data",
        "level": 2,
        "url": "#arbitrary-data"
      },
      {
        "text": "File Backend Example",
        "level": 2,
        "url": "#backend-file-example"
      },
      {
        "text": "Memcached Backend Example",
        "level": 2,
        "url": "#backend-memcached-example"
      },
      {
        "text": "Querying the cache",
        "level": 1,
        "url": "#read"
      },
      {
        "text": "Deleting data from the cache",
        "level": 1,
        "url": "#delete"
      },
      {
        "text": "Checking cache existence",
        "level": 1,
        "url": "#exists"
      },
      {
        "text": "Lifetime",
        "level": 1,
        "url": "#lifetime"
      },
      {
        "text": "Multi-Level Cache",
        "level": 1,
        "url": "#multi-level"
      },
      {
        "text": "Frontend Adapters",
        "level": 1,
        "url": "#adapters-frontend"
      },
      {
        "text": "Implementing your own Frontend adapters",
        "level": 2,
        "url": "#adapters-frontend-custom"
      },
      {
        "text": "Backend Adapters",
        "level": 1,
        "url": "#adapters-backend"
      },
      {
        "text": "Factory",
        "level": 2,
        "url": "#adapters-backend-factory"
      },
      {
        "text": "Implementing your own Backend adapters",
        "level": 2,
        "url": "#adapters-backend-custom"
      },
      {
        "text": "File Backend Options",
        "level": 2,
        "url": "#adapters-backend-file"
      },
      {
        "text": "Libmemcached Backend Options",
        "level": 2,
        "url": "#adapters-backend-libmemcached"
      },
      {
        "text": "Memcache Backend Options",
        "level": 2,
        "url": "#adapters-backend-memcache"
      },
      {
        "text": "APC Backend Options",
        "level": 2,
        "url": "#adapters-backend-apc"
      },
      {
        "text": "APCU Backend Options",
        "level": 2,
        "url": "#adapters-backend-apcu"
      },
      {
        "text": "Mongo Backend Options",
        "level": 2,
        "url": "#adapters-backend-mongo"
      },
      {
        "text": "XCache Backend Options",
        "level": 2,
        "url": "#adapters-backend-xcache"
      },
      {
        "text": "Redis Backend Options",
        "level": 2,
        "url": "#adapters-backend-redis"
      }
    ]
  },
  {
    "config": [
      {
        "text": "Reading Configurations",
        "level": 1,
        "url": "#overview"
      },
      {
        "text": "Factory",
        "level": 2,
        "url": "#factory"
      },
      {
        "text": "Native Arrays",
        "level": 1,
        "url": "#native-arrays"
      },
      {
        "text": "File Adapters",
        "level": 1,
        "url": "#file-adapter"
      },
      {
        "text": "Reading INI Files",
        "level": 1,
        "url": "#ini-files"
      },
      {
        "text": "URL Merging Configurations",
        "level": 1,
        "url": "#merging"
      },
      {
        "text": "Nested Configuration",
        "level": 1,
        "url": "#nested-configuration"
      },
      {
        "text": "Injecting Configuration Dependency",
        "level": 1,
        "url": ""
      }
    ]
  },
  {
    "contributions": [
      {
        "text": "Contributing to Phalcon",
        "level": 1,
        "url": "#contributing"
      },
      {
        "text": "Contributions",
        "level": 1,
        "url": "#contributions"
      },
      {
        "text": "Questions and Support",
        "level": 1,
        "url": "#file-adapter"
      },
      {
        "text": "Bug Report Checklist",
        "level": 1,
        "url": "#bug-report-checklist"
      },
      {
        "text": "Generating a backtrace",
        "level": 2,
        "url": "#bug-report-generating-backtrace"
      },
      {
        "text": "Pull Request Checklist",
        "level": 1,
        "url": "#pull-request-checklist"
      },
      {
        "text": "Getting Support",
        "level": 1,
        "url": "#getting-support"
      },
      {
        "text": "Requesting Features",
        "level": 1,
        "url": ""
      }
    ]
  },
  {
    "controllers": [
      {
        "text": "Overview",
        "level": 1,
        "url": "#overview"
      },
      {
        "text": "Using Controllers",
        "level": 1,
        "url": "#using"
      },
      {
        "text": "Dispatch Loop",
        "level": 1,
        "url": "#dispatch-loop"
      },
      {
        "text": "Initializing Controller",
        "level": 1,
        "url": "#initializing"
      },
      {
        "text": "Injecting Services",
        "level": 1,
        "url": "#injecting-services"
      },
      {
        "text": "Request and Response",
        "level": 1,
        "url": "#request-response"
      },
      {
        "text": "Session Data",
        "level": 1,
        "url": "#session-data"
      },
      {
        "text": "Using Services as Controllers",
        "level": 1,
        "url": "#services"
      },
      {
        "text": "Events in Controllers",
        "level": 1,
        "url": "#events"
      }
    ]
  },
  {
    "cookies": [
      {
        "text": "Cookies Management",
        "level": 1,
        "url": "#overview"
      },
      {
        "text": "Basic Usage",
        "level": 1,
        "url": "#usage"
      },
      {
        "text": "Encryption/Decryption of Cookies",
        "level": 1,
        "url": "#encryption-decryption"
      }
    ]
  },
  {
    "crypt": [
      {
        "text": "Encryption/Decryption",
        "level": 1,
        "url": "#overview"
      },
      {
        "text": "Basic Usage",
        "level": 1,
        "url": "#usage"
      },
      {
        "text": "Encryption Options",
        "level": 1,
        "url": "#options"
      },
      {
        "text": "Base64 Support",
        "level": 1,
        "url": "#base64"
      },
      {
        "text": "Setting up an Encryption service",
        "level": 1,
        "url": "#service"
      },
      {
        "text": "Links",
        "level": 1,
        "url": "#links"
      }
    ]
  },
  {
    "db-layer": [
      {
        "text": "Database Abstraction Layer",
        "level": 1,
        "url": "#overview"
      },
      {
        "text": "Database Adapters",
        "level": 1,
        "url": "#adapters"
      },
      {
        "text": "Factory",
        "level": 2,
        "url": "#adapters-factory"
      },
      {
        "text": "Implementing your own adapters",
        "level": 2,
        "url": "#adapters-custom"
      },
      {
        "text": "Database Dialects",
        "level": 1,
        "url": "#dialects"
      },
      {
        "text": "Implementing your own dialects",
        "level": 2,
        "url": "#dialects-custom"
      },
      {
        "text": "Connecting to Databases",
        "level": 1,
        "url": "#connection"
      },
      {
        "text": "Setting up additional PDO options",
        "level": 1,
        "url": "#options"
      },
      {
        "text": "Finding Rows",
        "level": 1,
        "url": "#finding-rows"
      },
      {
        "text": "Binding Parameters",
        "level": 1,
        "url": "#binding-parameters"
      },
      {
        "text": "Inserting/Updating/Deleting Rows",
        "level": 1,
        "url": "#crud"
      },
      {
        "text": "Transactions and Nested Transactions",
        "level": 1,
        "url": "#transactions"
      },
      {
        "text": "Database Events",
        "level": 1,
        "url": "#events"
      },
      {
        "text": "Profiling SQL Statements",
        "level": 1,
        "url": "#profiling"
      },
      {
        "text": "Logging SQL Statements",
        "level": 1,
        "url": "#logging-statements"
      },
      {
        "text": "Implementing your own Logger",
        "level": 1,
        "url": "#logger-custom"
      },
      {
        "text": "Describing Tables/Views",
        "level": 1,
        "url": "#describing-tables"
      },
      {
        "text": "Creating/Altering/Dropping Tables",
        "level": 1,
        "url": "#tables"
      },
      {
        "text": "Creating Tables",
        "level": 2,
        "url": "#tables-create"
      },
      {
        "text": "Altering Tables",
        "level": 2,
        "url": "#tables-altering"
      },
      {
        "text": "Dropping Tables",
        "level": 2,
        "url": "#tables-dropping"
      }
    ]
  },
  {
    "db-migrations": [
      {
        "text": "Database Migrations",
        "level": 1,
        "url": "#overview"
      },
      {
        "text": "Schema Dumping",
        "level": 1,
        "url": "#schema-dumping"
      },
      {
        "text": "Migration Class Anatomy",
        "level": 1,
        "url": "#class-anatomy"
      },
      {
        "text": "Defining Columns",
        "level": 2,
        "url": "#class-anatomy-columns"
      },
      {
        "text": "Defining Indexes",
        "level": 2,
        "url": "#class-anatomy-indexes"
      },
      {
        "text": "Defining References",
        "level": 2,
        "url": "#class-anatomy-references"
      },
      {
        "text": "Writing Migrations",
        "level": 1,
        "url": "#writing"
      },
      {
        "text": "Running Migrations",
        "level": 1,
        "url": "#running"
      }
    ]
  },
  {
    "db-models-behaviors": [
      {
        "text": "Model Behaviors",
        "level": 1,
        "url": "#overview"
      },
      {
        "text": "Timestampable",
        "level": 1,
        "url": "#timestampable"
      },
      {
        "text": "SoftDelete",
        "level": 1,
        "url": "#softdelete"
      },
      {
        "text": "Creating your own behaviors",
        "level": 1,
        "url": "#create-your-own-behaviors"
      },
      {
        "text": "Using Traits as behaviors",
        "level": 1,
        "url": "#traits-as-behaviors"
      }
    ]
  },
  {
    "db-models-cache": [
      {
        "text": "ORM Caching",
        "level": 1,
        "url": "#overview"
      },
      {
        "text": "Caching Resultsets",
        "level": 1,
        "url": "#caching-resultsets"
      },
      {
        "text": "Forcing Cache",
        "level": 1,
        "url": "#forcing-cache"
      },
      {
        "text": "Caching PHQL Queries",
        "level": 1,
        "url": "#caching-phql-queries"
      },
      {
        "text": "Reusable Related Records",
        "level": 1,
        "url": "#reusable-related-records"
      },
      {
        "text": "Caching Related Records",
        "level": 1,
        "url": "#caching-related-records"
      },
      {
        "text": "Caching Related Records Recursively",
        "level": 1,
        "url": "#caching-related-records-recursively"
      },
      {
        "text": "Caching based on Conditions",
        "level": 1,
        "url": "#caching-based-on-conditions"
      },
      {
        "text": "Caching PHQL execution plan",
        "level": 1,
        "url": "#caching-phql-execution-plan"
      }
    ]
  },
  {
    "db-models-events": [
      {
        "text": "Model Events",
        "level": 1,
        "url": "#overview"
      },
      {
        "text": "Events and Events Manager",
        "level": 1,
        "url": "#events"
      },
      {
        "text": "Implementing Events in the Model's class",
        "level": 2,
        "url": "#events-in-models"
      },
      {
        "text": "Using a custom Events Manager",
        "level": 2,
        "url": "#custom-events-manager"
      },
      {
        "text": "Logging Low-Level SQL Statements",
        "level": 1,
        "url": "#logging-sql-statements"
      },
      {
        "text": "Profiling SQL Statements",
        "level": 1,
        "url": "#profiling-sql-statements"
      }
    ]
  },
  {
    "db-models-metadata": [
      {
        "text": "Models Metadata",
        "level": 1,
        "url": "#overview"
      },
      {
        "text": "Caching Metadata",
        "level": 1,
        "url": "#caching-metadata"
      },
      {
        "text": "Metadata Strategies",
        "level": 1,
        "url": "#metadata-strategies"
      },
      {
        "text": "Database Introspection Strategy",
        "level": 2,
        "url": "#strategies-database-introspection"
      },
      {
        "text": "Annotations Strategy",
        "level": 2,
        "url": "#strategies-annotations"
      },
      {
        "text": "Manual Metadata",
        "level": 1,
        "url": "#strategies-manual"
      }
    ]
  },
  {
    "db-models-relationships": [
      {
        "text": "Model Relationships",
        "level": 1,
        "url": "#overview"
      },
      {
        "text": "Relationships between Models",
        "level": 1,
        "url": "#relationships"
      },
      {
        "text": "Unidirectional relationships",
        "level": 2,
        "url": "#unidirectional"
      },
      {
        "text": "Bidirectional relations",
        "level": 2,
        "url": "#bidirectional"
      },
      {
        "text": "Defining relationships",
        "level": 2,
        "url": "#defining"
      },
      {
        "text": "Multiple field relationships",
        "level": 3,
        "url": "#multiple-fields"
      },
      {
        "text": "Relationships with parameters",
        "level": 3,
        "url": "#parameters"
      },
      {
        "text": "Taking advantage of relationships",
        "level": 2,
        "url": "#taking-advantage-of"
      },
      {
        "text": "Aliasing Relationships",
        "level": 2,
        "url": "#aliases"
      },
      {
        "text": "Magic Getters vs. Explicit methods",
        "level": 3,
        "url": "#getters-vs-methods"
      },
      {
        "text": "Virtual Foreign Keys",
        "level": 1,
        "url": "#virtual-foreign-keys"
      },
      {
        "text": "Cascade/Restrict actions",
        "level": 2,
        "url": "#cascade-restrict-actions"
      },
      {
        "text": "Storing Related Records",
        "level": 1,
        "url": "#storing-related-records"
      },
      {
        "text": "Operations over Resultsets",
        "level": 1,
        "url": "#operations-over-resultsets"
      },
      {
        "text": "Updating related records",
        "level": 2,
        "url": "#updating-related-records"
      },
      {
        "text": "Deleting related records",
        "level": 2,
        "url": "#deleting-related-records"
      }
    ]
  },
  {
    "db-models-transactions": [
      {
        "text": "Model Transactions",
        "level": 1,
        "url": "#overview"
      },
      {
        "text": "Manual Transactions",
        "level": 1,
        "url": "#manual"
      },
      {
        "text": "Implicit Transactions",
        "level": 1,
        "url": "#implicit"
      },
      {
        "text": "Isolated Transactions",
        "level": 1,
        "url": "#isolated"
      }
    ]
  },
  {
    "db-models-validation": [
      {
        "text": "Model Transactions",
        "level": 1,
        "url": "#overview"
      },
      {
        "text": "Validating Data Integrity",
        "level": 1,
        "url": "#data-integrity"
      },
      {
        "text": "Validation Messages",
        "level": 1,
        "url": "#messages"
      },
      {
        "text": "Validation Failed Events",
        "level": 1,
        "url": "#failed-events"
      }
    ]
  },
  {
    "db-models": [
      {
        "text": "Working with Models",
        "level": 1,
        "url": "#working-with"
      },
      {
        "text": "Creating Models",
        "level": 1,
        "url": "#creating"
      },
      {
        "text": "Public properties vs. Setters/Getters",
        "level": 2,
        "url": "#properties-setters-getters"
      },
      {
        "text": "Understanding Records To Objects",
        "level": 1,
        "url": "#records-to-objects"
      },
      {
        "text": "Finding Records",
        "level": 1,
        "url": "#finding-records"
      },
      {
        "text": "Model Resultsets",
        "level": 2,
        "url": "#resultsets"
      },
      {
        "text": "Filtering Resultsets",
        "level": 2,
        "url": "#filters"
      },
      {
        "text": "Binding Parameters",
        "level": 2,
        "url": "#binding-parameters"
      },
      {
        "text": "Initializing/Preparing fetched records",
        "level": 1,
        "url": "#preparing-records"
      },
      {
        "text": "Generating Calculations",
        "level": 1,
        "url": "#calculations"
      },
      {
        "text": "Creating/Updating Records",
        "level": 1,
        "url": "#create-update-records"
      },
      {
        "text": "Create/Update with Confidence",
        "level": 2,
        "url": "#create-update-with-confidence"
      },
      {
        "text": "Deleting Records",
        "level": 1,
        "url": "#delete-records"
      },
      {
        "text": "Hydration Modes",
        "level": 1,
        "url": "#hydration-modes"
      },
      {
        "text": "Auto-generated identity columns",
        "level": 1,
        "url": "#identity-columns"
      },
      {
        "text": "Skipping Columns",
        "level": 1,
        "url": "#skipping-columns"
      },
      {
        "text": "Dynamic Updates",
        "level": 1,
        "url": "#dynamic-updates"
      },
      {
        "text": "Independent Column Mapping",
        "level": 1,
        "url": "#column-mapping"
      },
      {
        "text": "Record Snapshots",
        "level": 1,
        "url": "#record-snapshots"
      },
      {
        "text": "Pointing to a different schema",
        "level": 1,
        "url": "#different-schemas"
      },
      {
        "text": "Setting multiple databases",
        "level": 1,
        "url": "#multiple-databases"
      },
      {
        "text": "Injecting services into Models",
        "level": 1,
        "url": "#injecting-services-into-models"
      },
      {
        "text": "Disabling/Enabling Features",
        "level": 1,
        "url": "#disabling-enabling-features"
      },
      {
        "text": "Stand-Alone component",
        "level": 1,
        "url": "#stand-alone-component"
      }
    ]
  },
  {
    "db-odm": [
      {
        "text": "ODM (Object-Document Mapper)",
        "level": 1,
        "url": "#overview"
      },
      {
        "text": "Creating Models",
        "level": 1,
        "url": "#creating-models"
      },
      {
        "text": "Understanding Documents To Objects",
        "level": 1,
        "url": "#documents-to-objects"
      },
      {
        "text": "Models in Namespaces",
        "level": 1,
        "url": "#namespaces"
      },
      {
        "text": "Setting a Connection",
        "level": 1,
        "url": "#connection-setup"
      },
      {
        "text": "Finding Documents",
        "level": 1,
        "url": "#finding-documents"
      },
      {
        "text": "Aggregations",
        "level": 1,
        "url": "#aggregations"
      },
      {
        "text": "Creating Updating/Records",
        "level": 1,
        "url": "#creating-updating"
      },
      {
        "text": "Validation Messages",
        "level": 2,
        "url": "#validation-messages"
      },
      {
        "text": "Validation Events and Events Manager",
        "level": 2,
        "url": "#events"
      },
      {
        "text": "Implementing a Business Rule",
        "level": 2,
        "url": "#business-rules"
      },
      {
        "text": "Validating Data Integrity",
        "level": 2,
        "url": "#data-integrity"
      },
      {
        "text": "Deleting Records",
        "level": 1,
        "url": "#deleting-records"
      },
      {
        "text": "Validation Failed Events",
        "level": 1,
        "url": "#validation-failed-events"
      },
      {
        "text": "Implicit Ids vs. User Primary Keys",
        "level": 1,
        "url": "#ids-vs-primary-keys"
      },
      {
        "text": "Setting multiple databases",
        "level": 1,
        "url": "#multiple-databases"
      },
      {
        "text": "Injecting services into Models",
        "level": 1,
        "url": "#services-in-models"
      }
    ]
  },
  {
    "db-pagination": [
      {
        "text": "Pagination",
        "level": 1,
        "url": "#overview"
      },
      {
        "text": "Data Adapters",
        "level": 1,
        "url": "#data-adapters"
      },
      {
        "text": "Factory",
        "level": 1,
        "url": "#factory"
      },
      {
        "text": "Examples",
        "level": 1,
        "url": "#examples"
      },
      {
        "text": "Using Adapters",
        "level": 1,
        "url": "#using-adapters"
      },
      {
        "text": "Page Attributes",
        "level": 1,
        "url": "#page-attributes"
      },
      {
        "text": "Implementing your own adapters",
        "level": 1,
        "url": "#custom"
      }
    ]
  },
  {
    "db-phql": [
      {
        "text": "Phalcon Query Language (PHQL)",
        "level": 1,
        "url": "#overview"
      },
      {
        "text": "Usage Example",
        "level": 1,
        "url": "#usage"
      },
      {
        "text": "Creating PHQL Queries",
        "level": 1,
        "url": "#creating"
      },
      {
        "text": "Selecting Records",
        "level": 1,
        "url": "#selecting-records"
      },
      {
        "text": "Result Types",
        "level": 2,
        "url": "#result-types"
      },
      {
        "text": "Joins",
        "level": 2,
        "url": "#joins"
      },
      {
        "text": "Aggregations",
        "level": 2,
        "url": "#aggregations"
      },
      {
        "text": "Conditions",
        "level": 2,
        "url": "#conditions"
      },
      {
        "text": "Inserting Data",
        "level": 1,
        "url": "#inserting-data"
      },
      {
        "text": "Updating Data",
        "level": 1,
        "url": "#updating-data"
      },
      {
        "text": "Deleting Data",
        "level": 1,
        "url": "#deleting-data"
      },
      {
        "text": "Creating queries using the Query Builder",
        "level": 1,
        "url": "#query-builder"
      },
      {
        "text": "Bound Parameters",
        "level": 2,
        "url": "#query-builder-parameters"
      },
      {
        "text": "Disallow literals in PHQL",
        "level": 1,
        "url": "#disallow-literals"
      },
      {
        "text": "Escaping Reserved Words",
        "level": 1,
        "url": "#escaping-reserved-words"
      },
      {
        "text": "PHQL Lifecycle",
        "level": 1,
        "url": "#lifecycle"
      },
      {
        "text": "Using Raw SQL",
        "level": 1,
        "url": "#raw-sql"
      },
      {
        "text": "Troubleshooting",
        "level": 1,
        "url": "#troubleshooting"
      }
    ]
  },
  {
    "debug": [
      {
        "text": "Debugging Applications",
        "level": 1,
        "url": "#overview"
      },
      {
        "text": "Catching Exceptions",
        "level": 1,
        "url": "#catching-exceptions"
      },
      {
        "text": "Debug component",
        "level": 1,
        "url": "#debug-component"
      },
      {
        "text": "Reflection and Introspection",
        "level": 1,
        "url": "#reflection-introspection"
      },
      {
        "text": "Using XDebug",
        "level": 1,
        "url": "#xdebug"
      }
    ]
  },
  {
    "devtools-installation": [
      {
        "text": "DevTools on Linux",
        "level": 1,
        "url": "#overview"
      },
      {
        "text": "Prerequisites",
        "level": 1,
        "url": "#prerequisites"
      },
      {
        "text": "Installation",
        "level": 1,
        "url": "#installation"
      },
      {
        "text": "Linux",
        "level": 2,
        "url": "#installation-linux"
      },
      {
        "text": "MacOS",
        "level": 2,
        "url": "#installation-mac"
      },
      {
        "text": "Windows",
        "level": 2,
        "url": "#installation-windows"
      },
      {
        "text": "Adding PHP and Tools to your system PATH",
        "level": 3,
        "url": "#installation-windows-system-path"
      }
    ]
  },
  {
    "devtools-usage": [
      {
        "text": "Phalcon Developer Tools",
        "level": 1,
        "url": "#overview"
      },
      {
        "text": "Download",
        "level": 1,
        "url": "#download"
      },
      {
        "text": "Installation",
        "level": 1,
        "url": "#installation"
      },
      {
        "text": "Available Commands",
        "level": 1,
        "url": "#available-commands"
      },
      {
        "text": "Generating a Project Skeleton",
        "level": 1,
        "url": "#project-skeleton"
      },
      {
        "text": "Generating Controllers",
        "level": 1,
        "url": "#generating-controllers"
      },
      {
        "text": "Preparing Database Settings",
        "level": 1,
        "url": "#database-settings"
      },
      {
        "text": "Generating Models",
        "level": 1,
        "url": "#generating-models"
      },
      {
        "text": "Scaffold a CRUD",
        "level": 1,
        "url": "#crud"
      },
      {
        "text": "Web Interface to Tools",
        "level": 1,
        "url": "#web-interface"
      },
      {
        "text": "Integrating Tools with PhpStorm IDE",
        "level": 1,
        "url": "#phpstorm-ide"
      },
      {
        "text": "Conclusion",
        "level": 1,
        "url": "#conclusion"
      }
    ]
  },
  {
    "di": [
      {
        "text": "Dependency Injection / Service Location",
        "level": 1,
        "url": "#di-service-location"
      },
      {
        "text": "DI explained",
        "level": 1,
        "url": "#di-explained"
      },
      {
        "text": "Registering services in the Container",
        "level": 1,
        "url": "#registering-services"
      },
      {
        "text": "Simple Registration",
        "level": 2,
        "url": "#simple-registration"
      },
      {
        "text": "String",
        "level": 3,
        "url": "#simple-registration-string"
      },
      {
        "text": "Class instances",
        "level": 3,
        "url": "#class-instances"
      },
      {
        "text": "Closures/Anonymous functions",
        "level": 3,
        "url": "#closures-anonymous-functions"
      },
      {
        "text": "Complex Registration",
        "level": 2,
        "url": "#complex-registration"
      },
      {
        "text": "Constructor Injection",
        "level": 3,
        "url": "#constructor-injection"
      },
      {
        "text": "Setter Injection",
        "level": 3,
        "url": "#setter-injection"
      },
      {
        "text": "Properties Injection",
        "level": 3,
        "url": "#properties-injection"
      },
      {
        "text": "Array Syntax",
        "level": 2,
        "url": "#array-syntax"
      },
      {
        "text": "Resolving Services",
        "level": 1,
        "url": "#resolving-services"
      },
      {
        "text": "Events",
        "level": 2,
        "url": "#events"
      },
      {
        "text": "Shared services",
        "level": 1,
        "url": "#shared-services"
      },
      {
        "text": "Manipulating services individually",
        "level": 1,
        "url": "#manipulating-services-individually"
      },
      {
        "text": "Instantiating classes via the Service Container",
        "level": 1,
        "url": "#instantiating-classes-service-container"
      },
      {
        "text": "Automatic Injecting of the DI itself",
        "level": 1,
        "url": "#automatic-injecting-di-itself"
      },
      {
        "text": "Organizing services in files",
        "level": 1,
        "url": "#organizing-services-files"
      },
      {
        "text": "Accessing the DI in a static way",
        "level": 1,
        "url": "#accessing-di-static-way"
      },
      {
        "text": "Factory Default DI",
        "level": 1,
        "url": "#factory-default-di"
      },
      {
        "text": "Service Name Conventions",
        "level": 1,
        "url": "#service-name-conventions"
      },
      {
        "text": "Implementing your own DI",
        "level": 1,
        "url": "#implementing-your-own-di"
      }
    ]
  },
  {
    "dispatcher": [
      {
        "text": "Dispatching Controllers",
        "level": 1,
        "url": "#explained"
      },
      {
        "text": "The Dispatch Loop",
        "level": 1,
        "url": "#dispatch-loop"
      },
      {
        "text": "Dispatch Loop Events",
        "level": 2,
        "url": "#dispatch-loop-events"
      },
      {
        "text": "Forwarding to other actions",
        "level": 1,
        "url": "#forwarding"
      },
      {
        "text": "Preparing Parameters",
        "level": 1,
        "url": "#preparing-parameters"
      },
      {
        "text": "Getting Parameters",
        "level": 1,
        "url": "#getting-parameters"
      },
      {
        "text": "Preparing actions",
        "level": 1,
        "url": "#preparing-actions"
      },
      {
        "text": "Camelize action names",
        "level": 2,
        "url": "#preparing-actions-camelizing-action-names"
      },
      {
        "text": "Remove legacy extensions",
        "level": 2,
        "url": "#preparing-actions-removing-legacy-extensions"
      },
      {
        "text": "Inject model instances",
        "level": 2,
        "url": "#preparing-actions-inject-model-instances"
      },
      {
        "text": "Handling Not-Found Exceptions",
        "level": 1,
        "url": "#handling-404"
      },
      {
        "text": "Implementing your own Dispatcher",
        "level": 1,
        "url": "#custom"
      }
    ]
  },
  {
    "environments-docker": [
      {
        "text": "Environments - Docker",
        "level": 1,
        "url": "#overview"
      },
      {
        "text": "Dependencies",
        "level": 1,
        "url": "#dependencies"
      },
      {
        "text": "Services",
        "level": 1,
        "url": "#services"
      },
      {
        "text": "Installation",
        "level": 1,
        "url": "#installation"
      },
      {
        "text": "With Composer (recommended)",
        "level": 2,
        "url": "#installation-composer"
      },
      {
        "text": "With Git",
        "level": 2,
        "url": "#installation-git"
      },
      {
        "text": "Configuration",
        "level": 1,
        "url": "#configuration"
      },
      {
        "text": "Usage",
        "level": 1,
        "url": "#usage"
      },
      {
        "text": "Set up",
        "level": 1,
        "url": "#setup"
      },
      {
        "text": "Logs",
        "level": 1,
        "url": "#logs"
      },
      {
        "text": "Environment variables",
        "level": 1,
        "url": "#environment-variables"
      },
      {
        "text": "Web environment",
        "level": 2,
        "url": "#environment-variables-web"
      },
      {
        "text": "phpMyAdmin variables",
        "level": 2,
        "url": "#environment-variables-phpmyadmin"
      },
      {
        "text": "Xdebug Remote debugger (PhpStorm)",
        "level": 1,
        "url": "#xdebug"
      },
      {
        "text": "Troubleshooting",
        "level": 1,
        "url": "#troubleshooting"
      },
      {
        "text": "Startup or linking errors",
        "level": 2,
        "url": "#troubleshooting-startup"
      },
      {
        "text": "Full reset",
        "level": 2,
        "url": "#troubleshooting-full-reset"
      },
      {
        "text": "Updating dependencies",
        "level": 2,
        "url": "#troubleshooting-dependencies"
      },
      {
        "text": "Versions",
        "level": 1,
        "url": "#versions"
      }
    ]
  },
  {
    "environments-nanobox": [
      {
        "text": "Environments - Nanobox",
        "level": 1,
        "url": "#overview"
      },
      {
        "text": "Create a New Project",
        "level": 1,
        "url": "#create-project"
      },
      {
        "text": "Add a `boxfile.yml`",
        "level": 1,
        "url": "#boxfile-yml"
      },
      {
        "text": "Add Phalcon Devtools to your `composer.json`",
        "level": 1,
        "url": "#add-devtools"
      },
      {
        "text": "Start Nanobox and Generate a New Phalcon App",
        "level": 1,
        "url": "#new-phalcon-app"
      },
      {
        "text": "Run the App Locally",
        "level": 1,
        "url": "#run-app"
      },
      {
        "text": "Check Out the Environment",
        "level": 1,
        "url": "#environment"
      },
      {
        "text": "Phalcon and Nanobox",
        "level": 1,
        "url": "#conclusion"
      }
    ]
  },
  {
    "environments-vagrant": [
      {
        "text": "Environments - Vagrant",
        "level": 1,
        "url": "#overview"
      },
      {
        "text": "Requirements",
        "level": 1,
        "url": "#requirements"
      },
      {
        "text": "Packages Included",
        "level": 1,
        "url": "#packages-included"
      },
      {
        "text": "Installation",
        "level": 1,
        "url": "#installation"
      },
      {
        "text": "Installing the Vagrant Box",
        "level": 2,
        "url": "#installation-vagrant-box"
      },
      {
        "text": "Installing the Phalcon Box",
        "level": 2,
        "url": "#installation-phalcon-box"
      },
      {
        "text": "Configuring",
        "level": 1,
        "url": "#installation-configuration"
      },
      {
        "text": "Setting your provider",
        "level": 2,
        "url": "#installation-configuration-setting-provider"
      },
      {
        "text": "Memory and CPU",
        "level": 2,
        "url": "#installation-configuration-memory-cpu"
      },
      {
        "text": "Shared folders",
        "level": 2,
        "url": "#installation-configuration-shared-folders"
      },
      {
        "text": "Nginx sites",
        "level": 2,
        "url": "#installation-configuration-nginx"
      },
      {
        "text": "Custom Nginx configuration",
        "level": 3,
        "url": "#installation-configuration-custom-nginx"
      },
      {
        "text": "Configuring the `hosts` file",
        "level": 3,
        "url": "#installation-configuration-hosts"
      },
      {
        "text": "Install additional packages",
        "level": 2,
        "url": "#installation-aditional-packages"
      },
      {
        "text": "Launching the Phalcon Box",
        "level": 2,
        "url": "#installation-launching-phalcon-box"
      },
      {
        "text": "Daily usage",
        "level": 1,
        "url": "#daily-usage"
      },
      {
        "text": "Accessing Phalcon Box globally",
        "level": 2,
        "url": "#daily-usage-accessing-box-globally"
      },
      {
        "text": "Mac || Linux",
        "level": 3,
        "url": "#daily-usage-accessing-box-globally-mac-linux"
      },
      {
        "text": "Windows",
        "level": 3,
        "url": "#daily-usage-accessing-box-globally-windows"
      },
      {
        "text": "Connecting via SSH",
        "level": 2,
        "url": "#daily-usage-ssh"
      },
      {
        "text": "Connecting to databases",
        "level": 2,
        "url": "#daily-usage-databases"
      },
      {
        "text": "Adding additional sites",
        "level": 2,
        "url": "#daily-usage-additional-sites"
      },
      {
        "text": "Environment variables",
        "level": 2,
        "url": "#daily-usage-environment-variables"
      },
      {
        "text": "Global variables",
        "level": 3,
        "url": "#daily-usage-environment-global-variables"
      },
      {
        "text": "Site variables",
        "level": 3,
        "url": "#daily-usage-environment-site-variables"
      },
      {
        "text": "Ports",
        "level": 2,
        "url": "#daily-usage-ports"
      },
      {
        "text": "Forwarding additional ports",
        "level": 3,
        "url": "#daily-usage-ports-forwarding"
      },
      {
        "text": "Sharing your environment",
        "level": 2,
        "url": "#daily-usage-sharing-environment"
      },
      {
        "text": "Network interfaces",
        "level": 2,
        "url": "#daily-usage-network-interfaces"
      },
      {
        "text": "Updating Phalcon Box",
        "level": 2,
        "url": "#daily-usage-updating-box"
      },
      {
        "text": "Provider specific settings",
        "level": 2,
        "url": "#daily-usage-provider-settings"
      },
      {
        "text": "VirtualBox",
        "level": 3,
        "url": "#daily-usage-provider-settings-virtualbox"
      },
      {
        "text": "Mail catcher",
        "level": 2,
        "url": "#daily-usage-mail-catcher"
      },
      {
        "text": "Troubleshooting",
        "level": 1,
        "url": "#troubleshooting"
      }
    ]
  },
  {
    "escaper": [
      {
        "text": "Contextual Escaping",
        "level": 1,
        "url": "#overview"
      },
      {
        "text": "Escaping HTML",
        "level": 1,
        "url": "#html"
      },
      {
        "text": "Escaping HTML Attributes",
        "level": 1,
        "url": "#html-attributes"
      },
      {
        "text": "Escaping URLs",
        "level": 1,
        "url": "#urls"
      },
      {
        "text": "Escaping CSS",
        "level": 1,
        "url": "#css"
      },
      {
        "text": "Escaping JavaScript",
        "level": 1,
        "url": "#javascript"
      }
    ]
  },
  {
    "events": [
      {
        "text": "Events Manager",
        "level": 1,
        "url": "#overview"
      },
      {
        "text": "Naming Convention",
        "level": 1,
        "url": "#naming-convention"
      },
      {
        "text": "Usage Example",
        "level": 1,
        "url": "#usage"
      },
      {
        "text": "Creating components that trigger Events",
        "level": 1,
        "url": "#components-that-trigger-events"
      },
      {
        "text": "Using Services From The DI",
        "level": 1,
        "url": "#using-services"
      },
      {
        "text": "Event Propagation/Cancellation",
        "level": 1,
        "url": "#propagation-cancellation"
      },
      {
        "text": "Listener Priorities",
        "level": 1,
        "url": "#listener-priorities"
      },
      {
        "text": "Collecting Responses",
        "level": 1,
        "url": "#collecting-responses"
      },
      {
        "text": "Implementing your own EventsManager",
        "level": 1,
        "url": "#custom"
      },
      {
        "text": "List of events",
        "level": 1,
        "url": "#list"
      }
    ]
  },
  {
    "filter": [
      {
        "text": "Filtering and Sanitizing",
        "level": 1,
        "url": "#overview"
      },
      {
        "text": "Types of Built-in Filters",
        "level": 1,
        "url": "#types"
      },
      {
        "text": "Sanitizing data",
        "level": 1,
        "url": "#sanitizing"
      },
      {
        "text": "Sanitizing from Controllers",
        "level": 1,
        "url": "#sanitizing-from-controllers"
      },
      {
        "text": "Filtering Action Parameters",
        "level": 1,
        "url": "#filtering-action-parameters"
      },
      {
        "text": "Filtering data",
        "level": 1,
        "url": "#filtering-data"
      },
      {
        "text": "Combining Filters",
        "level": 1,
        "url": "#combining-filters"
      },
      {
        "text": "Adding filters",
        "level": 1,
        "url": "#adding-filters"
      },
      {
        "text": "Complex Sanitizing and Filtering",
        "level": 1,
        "url": "#complex-sanitization-filtering"
      },
      {
        "text": "Implementing your own Filter",
        "level": 1,
        "url": "#custom"
      }
    ]
  },
  {
    "flash": [
      {
        "text": "Flashing Messages",
        "level": 1,
        "url": "#overview"
      },
      {
        "text": "Adapters",
        "level": 1,
        "url": "#adapters"
      },
      {
        "text": "Usage",
        "level": 1,
        "url": "#usage"
      },
      {
        "text": "Printing Messages",
        "level": 1,
        "url": "#printing"
      },
      {
        "text": "Implicit Flush vs. Session",
        "level": 1,
        "url": "#implicit-flush-vs-session"
      }
    ]
  },
  {
    "forms": [
      {
        "text": "Forms",
        "level": 1,
        "url": "#overview"
      },
      {
        "text": "Initializing forms",
        "level": 1,
        "url": "#initializing"
      },
      {
        "text": "Filtering",
        "level": 1,
        "url": "#filtering"
      },
      {
        "text": "Forms + Entities",
        "level": 1,
        "url": "#entities"
      },
      {
        "text": "Form Elements",
        "level": 1,
        "url": "#elements"
      },
      {
        "text": "Event Callbacks",
        "level": 1,
        "url": "#event-callback"
      },
      {
        "text": "Rendering Forms",
        "level": 1,
        "url": "#rendering"
      },
      {
        "text": "Creating Form Elements",
        "level": 1,
        "url": "#creating-elements"
      },
      {
        "text": "Forms Manager",
        "level": 1,
        "url": "#manager"
      },
      {
        "text": "External Resources",
        "level": 1,
        "url": "#external"
      }
    ]
  },
  {
    "i18n": [
      {
        "text": "Internationalization",
        "level": 1,
        "url": "#overview"
      },
      {
        "text": "Find out best available Locale",
        "level": 1,
        "url": "#best-locale"
      },
      {
        "text": "Formatting messages based on Locale",
        "level": 1,
        "url": "#formatting-messages"
      },
      {
        "text": "Locale-Sensitive comparison",
        "level": 1,
        "url": "#locale-comparison"
      },
      {
        "text": "Transliteration",
        "level": 1,
        "url": "#transliteration"
      }
    ]
  },
  {
    "image": [
      {
        "text": "Images",
        "level": 1,
        "url": "#overview"
      },
      {
        "text": "Adapters",
        "level": 1,
        "url": "#adapters"
      },
      {
        "text": "Factory",
        "level": 2,
        "url": "#adapters-factory"
      },
      {
        "text": "Implementing your own adapters",
        "level": 2,
        "url": "#adapters-custom"
      },
      {
        "text": "Saving and rendering images",
        "level": 1,
        "url": "#saving-rendering"
      },
      {
        "text": "Resizing images",
        "level": 1,
        "url": "#resizing"
      },
      {
        "text": "`Image::WIDTH`",
        "level": 2,
        "url": "#resizing-width"
      },
      {
        "text": "`Image::HEIGHT`",
        "level": 2,
        "url": "#resizing-height"
      },
      {
        "text": "`Image::NONE`",
        "level": 2,
        "url": "#resizing-none"
      },
      {
        "text": "`Image::TENSILE`",
        "level": 2,
        "url": "#resizing-tensile"
      },
      {
        "text": "Cropping images",
        "level": 1,
        "url": "#cropping"
      },
      {
        "text": "Rotating images",
        "level": 1,
        "url": "#rotating"
      },
      {
        "text": "Flipping images",
        "level": 1,
        "url": "#flipping"
      },
      {
        "text": "Sharpening images",
        "level": 1,
        "url": "#sharpening"
      },
      {
        "text": "Adding watermarks to images",
        "level": 1,
        "url": "#watermarks"
      },
      {
        "text": "Blurring images",
        "level": 1,
        "url": "#blurring"
      },
      {
        "text": "Pixelating images",
        "level": 1,
        "url": "#pixelating"
      }
    ]
  },
  {
    "installation": [
      {
        "text": "Requirements",
        "level": 1,
        "url": "#requirements"
      },
      {
        "text": "Installation",
        "level": 1,
        "url": "#installation"
      }
    ]
  },
  {
    "loader": [
      {
        "text": "Requirements",
        "level": 1,
        "url": "#overview"
      },
      {
        "text": "Security Layer",
        "level": 1,
        "url": "#security"
      },
      {
        "text": "Registering Namespaces",
        "level": 1,
        "url": "#registering-namespaces"
      },
      {
        "text": "Registering Directories",
        "level": 1,
        "url": "#registering-directories"
      },
      {
        "text": "Registering Classes",
        "level": 1,
        "url": "#registering-classes"
      },
      {
        "text": "Registering Files",
        "level": 1,
        "url": "#registering-files"
      },
      {
        "text": "Additional file extensions",
        "level": 1,
        "url": "#registering-file-extensions"
      },
      {
        "text": "Modifying current strategies",
        "level": 1,
        "url": "#modifying-current-strategies"
      },
      {
        "text": "Autoloading Events",
        "level": 1,
        "url": "#events"
      },
      {
        "text": "Troubleshooting",
        "level": 1,
        "url": "#troubleshooting"
      }
    ]
  },
  {
    "logging": [
      {
        "text": "Logging",
        "level": 1,
        "url": "#overview"
      },
      {
        "text": "Adapters",
        "level": 1,
        "url": "#adapters"
      },
      {
        "text": "Factory",
        "level": 2,
        "url": "#adapters-factory"
      },
      {
        "text": "Creating a Log",
        "level": 1,
        "url": "#creating"
      },
      {
        "text": "Transactions",
        "level": 1,
        "url": "#transactions"
      },
      {
        "text": "Logging to Multiple Handlers",
        "level": 1,
        "url": "#multiple-handlers"
      },
      {
        "text": "Message Formatting",
        "level": 1,
        "url": "#message-formatting"
      },
      {
        "text": "Line Formatter",
        "level": 2,
        "url": "#message-formatting-line"
      },
      {
        "text": "Implementing your own formatters",
        "level": 2,
        "url": "#message-formatting-custom"
      },
      {
        "text": "Adapters",
        "level": 1,
        "url": "#usage"
      },
      {
        "text": "Stream Logger",
        "level": 2,
        "url": "#usage-stream"
      },
      {
        "text": "File Logger",
        "level": 2,
        "url": "#usage-file"
      },
      {
        "text": "Syslog Logger",
        "level": 2,
        "url": "#usage-syslog"
      },
      {
        "text": "FirePHP Logger",
        "level": 2,
        "url": "#usage-firephp"
      },
      {
        "text": "Implementing your own adapters",
        "level": 2,
        "url": "#usage-custom"
      }
    ]
  },
  {
    "mvc": [
      {
        "text": "The MVC Architecture",
        "level": 1,
        "url": "#architecture"
      },
      {
        "text": "Models",
        "level": 1,
        "url": "#models"
      },
      {
        "text": "Views",
        "level": 1,
        "url": "#views"
      },
      {
        "text": "Controllers",
        "level": 1,
        "url": "#controllers"
      }
    ]
  },
  {
    "namespaces": [
      {
        "text": "Working with Namespaces",
        "level": 1,
        "url": "#setting-up"
      },
      {
        "text": "Setting up the framework",
        "level": 1,
        "url": "#models"
      },
      {
        "text": "Controllers in Namespaces",
        "level": 1,
        "url": "#controllers"
      },
      {
        "text": "Models in Namespaces",
        "level": 1,
        "url": "#models"
      }
    ]
  },
  {
    "performance": [
      {
        "text": "Increasing Performance",
        "level": 1,
        "url": "#overview"
      },
      {
        "text": "Profile on the Server",
        "level": 1,
        "url": "#profiling-server"
      },
      {
        "text": "Profiling with Xhprof",
        "level": 2,
        "url": "#profiling-server-xhprof"
      },
      {
        "text": "Profiling SQL Statements",
        "level": 2,
        "url": "#profiling-server-sql-statements"
      },
      {
        "text": "Profile on the Client",
        "level": 1,
        "url": "#profiling-client"
      },
      {
        "text": "Profile with Chrome/Firefox",
        "level": 2,
        "url": "#profiling-client-chrome-firefox"
      },
      {
        "text": "Yahoo! YSlow",
        "level": 2,
        "url": "#profiling-client-yslow"
      },
      {
        "text": "Profile with Speed Tracer",
        "level": 2,
        "url": "#profiling-client-speed-tracer"
      },
      {
        "text": "Use a recent PHP version",
        "level": 1,
        "url": "#php-version"
      },
      {
        "text": "Use a PHP Bytecode Cache",
        "level": 1,
        "url": "#bytecode-cache"
      },
      {
        "text": "Do blocking work in the background",
        "level": 1,
        "url": "#background-tasks"
      },
      {
        "text": "Google Page Speed",
        "level": 1,
        "url": "#page-speed"
      }
    ]
  },
  {
    "queue": [
      {
        "text": "Queueing",
        "level": 1,
        "url": "#overview"
      },
      {
        "text": "Putting Jobs into the Queue",
        "level": 1,
        "url": "#put-jobs-in-queue"
      },
      {
        "text": "Retrieving Messages",
        "level": 1,
        "url": "#retrieving-messages"
      }
    ]
  },
  {
    "reproducible-tests": [
      {
        "text": "Creating a small script",
        "level": 1,
        "url": "#overview"
      },
      {
        "text": "Database",
        "level": 1,
        "url": "#database"
      },
      {
        "text": "Single/Multi-Module applications",
        "level": 1,
        "url": "#single-multi"
      },
      {
        "text": "Micro application",
        "level": 1,
        "url": "#micro"
      },
      {
        "text": "ORM",
        "level": 1,
        "url": "#orm"
      }
    ]
  },
  {
    "request": [
      {
        "text": "Request Environment",
        "level": 1,
        "url": "#overview"
      },
      {
        "text": "Getting Values",
        "level": 1,
        "url": "#getting-values"
      },
      {
        "text": "Accessing the Request from Controllers",
        "level": 1,
        "url": "#controller-access"
      },
      {
        "text": "Uploading Files",
        "level": 1,
        "url": "#uploading-files"
      },
      {
        "text": "Working with Headers",
        "level": 1,
        "url": "#working-with-headers"
      }
    ]
  },
  {
    "response": [
      {
        "text": "Returning Responses",
        "level": 1,
        "url": "#overview"
      },
      {
        "text": "Working with Headers",
        "level": 1,
        "url": "#working-with-headers"
      },
      {
        "text": "Making Redirections",
        "level": 1,
        "url": "#redirections"
      },
      {
        "text": "HTTP Cache",
        "level": 1,
        "url": "#http-cache"
      },
      {
        "text": "Setting an Expiration Time",
        "level": 2,
        "url": "#http-cache-expiration-time"
      },
      {
        "text": "Cache-Control",
        "level": 2,
        "url": "#http-cache-control"
      },
      {
        "text": "E-Tag",
        "level": 2,
        "url": "#http-cache-etag"
      }
    ]
  },
  {
    "routing": [
      {
        "text": "Routing",
        "level": 1,
        "url": "#overview"
      },
      {
        "text": "Defining Routes",
        "level": 1,
        "url": "#defining"
      },
      {
        "text": "Parameters with Names",
        "level": 2,
        "url": "#defining-named-parameters"
      },
      {
        "text": "Short Syntax",
        "level": 2,
        "url": "#defining-short-syntax"
      },
      {
        "text": "Mixing Array and Short Syntax",
        "level": 2,
        "url": "#defining-mixed-parameters"
      },
      {
        "text": "Routing to Modules",
        "level": 2,
        "url": "#defining-route-to-modules"
      },
      {
        "text": "HTTP Method Restrictions",
        "level": 2,
        "url": "#defining-http-method-restrictions"
      },
      {
        "text": "Using conversors",
        "level": 2,
        "url": "#defining-using-conversors"
      },
      {
        "text": "Groups of Routes",
        "level": 2,
        "url": "#defining-groups-of-routes"
      },
      {
        "text": "Matching Routes",
        "level": 1,
        "url": "#matching"
      },
      {
        "text": "Naming Routes",
        "level": 1,
        "url": "#naming"
      },
      {
        "text": "Usage Examples",
        "level": 1,
        "url": "#usage"
      },
      {
        "text": "Default Behavior",
        "level": 1,
        "url": "#default-behavior"
      },
      {
        "text": "Setting the default route",
        "level": 1,
        "url": "#default-route"
      },
      {
        "text": "Not Found Paths",
        "level": 1,
        "url": "#not-found-paths"
      },
      {
        "text": "Setting default paths",
        "level": 1,
        "url": "#default-paths"
      },
      {
        "text": "Dealing with extra/trailing slashes",
        "level": 1,
        "url": "#extra-slashes"
      },
      {
        "text": "Match Callbacks",
        "level": 1,
        "url": "#callbacks"
      },
      {
        "text": "Hostname Constraints",
        "level": 1,
        "url": "#hostname-constraints"
      },
      {
        "text": "URI Sources",
        "level": 1,
        "url": "#uri-sources"
      },
      {
        "text": "Testing your routes",
        "level": 1,
        "url": "#testing"
      },
      {
        "text": "Annotations Router",
        "level": 1,
        "url": "#annotations"
      },
      {
        "text": "Registering Router instance",
        "level": 1,
        "url": "#registration"
      },
      {
        "text": "Implementing your own Router",
        "level": 1,
        "url": "#custom"
      }
    ]
  },
  {
    "security": [
      {
        "text": "Security",
        "level": 1,
        "url": "#overview"
      },
      {
        "text": "Password Hashing",
        "level": 1,
        "url": "#hashing"
      },
      {
        "text": "Cross-Site Request Forgery (CSRF) protection",
        "level": 1,
        "url": "#csrf"
      },
      {
        "text": "Setting up the component",
        "level": 1,
        "url": "#setup"
      },
      {
        "text": "Random",
        "level": 1,
        "url": "#random"
      },
      {
        "text": "External Resources",
        "level": 1,
        "url": "#resources"
      }
    ]
  },
  {
    "session": [
      {
        "text": "Storing data in the Session",
        "level": 1,
        "url": "#overview"
      },
      {
        "text": "Starting the Session",
        "level": 1,
        "url": "#start"
      },
      {
        "text": "Factory",
        "level": 2,
        "url": "#start-factory"
      },
      {
        "text": "XAMPP",
        "level": 1,
        "url": "#overview"
      },
      {
        "text": "Storing/Retrieving data in Session",
        "level": 1,
        "url": "#store"
      },
      {
        "text": "Removing/Destroying Sessions",
        "level": 1,
        "url": "#remove-destroy"
      },
      {
        "text": "Isolating Session Data between Applications",
        "level": 1,
        "url": "#data-isolation"
      },
      {
        "text": "Session Bags",
        "level": 1,
        "url": "#bags"
      },
      {
        "text": "Persistent Data in Components",
        "level": 1,
        "url": "#data-persistence"
      },
      {
        "text": "Implementing your own adapters",
        "level": 1,
        "url": "#custom-adapters"
      }
    ]
  },
  {
    "tag": [
      {
        "text": "View Helpers (Tags)",
        "level": 1,
        "url": "#overview"
      },
      {
        "text": "Document Type of Content",
        "level": 1,
        "url": "#document-type"
      },
      {
        "text": "Creating Forms",
        "level": 1,
        "url": "#creating-forms"
      },
      {
        "text": "Helpers to Generate Form Elements",
        "level": 1,
        "url": "#helpers-for-form-elements"
      },
      {
        "text": "Making Select Boxes",
        "level": 1,
        "url": "#select-boxes"
      },
      {
        "text": "Assigning HTML attributes",
        "level": 1,
        "url": "#html-attributes"
      },
      {
        "text": "Setting Helper Values",
        "level": 1,
        "url": "#helper-values"
      },
      {
        "text": "From Controllers",
        "level": 2,
        "url": "#helper-values-form-controllers"
      },
      {
        "text": "From the Request",
        "level": 2,
        "url": "#helper-values-from-request"
      },
      {
        "text": "Specifying values directly",
        "level": 2,
        "url": "#helper-values-directly"
      },
      {
        "text": "Changing dynamically the Document Title",
        "level": 1,
        "url": "#changing-document-title-dynamically"
      },
      {
        "text": "Static Content Helpers",
        "level": 1,
        "url": "#static-content-helpers"
      },
      {
        "text": "Images",
        "level": 2,
        "url": "#static-content-helpers-images"
      },
      {
        "text": "Stylesheets",
        "level": 2,
        "url": "#static-content-helpers-stylesheets"
      },
      {
        "text": "Javascript",
        "level": 2,
        "url": "#static-content-helpers-javascript"
      },
      {
        "text": "HTML5 elements - generic HTML helper",
        "level": 2,
        "url": "#static-content-helpers-html5"
      },
      {
        "text": "Tag Service",
        "level": 1,
        "url": "#tag-helpers"
      },
      {
        "text": "Creating your own helpers",
        "level": 1,
        "url": "#custom-helpers"
      }
    ]
  },
  {
    "translate": [
      {
        "text": "Multi-lingual Support",
        "level": 1,
        "url": "#overview"
      },
      {
        "text": "Adapters",
        "level": 1,
        "url": "#adapters"
      },
      {
        "text": "Factory",
        "level": 2,
        "url": "#adapters-factory"
      },
      {
        "text": "Component Usage",
        "level": 1,
        "url": "#usage"
      },
      {
        "text": "Implementing your own adapters",
        "level": 1,
        "url": "#custom"
      }
    ]
  },
  {
    "tutorial-base": [
      {
        "text": "View",
        "level": 1,
        "url": "#basic"
      },
      {
        "text": "File structure",
        "level": 1,
        "url": "#file-structure"
      },
      {
        "text": "Bootstrap",
        "level": 1,
        "url": "#bootstrap"
      },
      {
        "text": "Autoloaders",
        "level": 2,
        "url": "#autoloaders"
      },
      {
        "text": "Dependency Management",
        "level": 2,
        "url": "#dependency-management"
      },
      {
        "text": " - [Handling the application request",
        "level": 2,
        "url": "#request"
      },
      {
        "text": " - [Putting everything together",
        "level": 2,
        "url": "#full-example"
      },
      {
        "text": "Creating a Controller",
        "level": 1,
        "url": "#controller"
      },
      {
        "text": "Sending output to a view",
        "level": 1,
        "url": "#view"
      },
      {
        "text": "Designing a sign up form",
        "level": 1,
        "url": "#signup-form"
      },
      {
        "text": "Creating a Model",
        "level": 1,
        "url": "#model"
      },
      {
        "text": "Setting a Database Connection",
        "level": 1,
        "url": "#database-connection"
      },
      {
        "text": "Storing data using models",
        "level": 1,
        "url": "#storing-data"
      },
      {
        "text": "Conclusion",
        "level": 1,
        "url": "#conclusion"
      }
    ]
  },
  {
    "tutorial-invo": [
      {
        "text": "Tutorial: INVO",
        "level": 1,
        "url": "#overview"
      },
      {
        "text": "Project Structure",
        "level": 1,
        "url": "#structure"
      },
      {
        "text": "Routing",
        "level": 1,
        "url": "#routing"
      },
      {
        "text": "Configuration",
        "level": 1,
        "url": "#configuration"
      },
      {
        "text": "Autoloaders",
        "level": 1,
        "url": "#autoloaders"
      },
      {
        "text": "Registering services",
        "level": 1,
        "url": "#services"
      },
      {
        "text": "Handling the Request",
        "level": 1,
        "url": "#handling-requests"
      },
      {
        "text": "Dependency Injection",
        "level": 1,
        "url": "#dependency-injection"
      },
      {
        "text": "Log into the Application",
        "level": 1,
        "url": "#log-in"
      },
      {
        "text": "Securing the Backend",
        "level": 1,
        "url": "#securing-backend"
      },
      {
        "text": "Events Management",
        "level": 2,
        "url": "#events-manager"
      },
      {
        "text": "Getting the ACL list",
        "level": 2,
        "url": "#acl"
      },
      {
        "text": "Working with the CRUD",
        "level": 1,
        "url": "#working-with-crud"
      },
      {
        "text": "The Search Form",
        "level": 1,
        "url": "#search-form"
      },
      {
        "text": "Performing a Search",
        "level": 1,
        "url": "#performing-searches"
      },
      {
        "text": "Creating and Updating Records",
        "level": 1,
        "url": "#creating-updating-records"
      },
      {
        "text": "User Components",
        "level": 1,
        "url": "#user-components"
      },
      {
        "text": "Changing the Title Dynamically",
        "level": 1,
        "url": "#dynamic-titles"
      }
    ]
  },
  {
    "tutorial-rest": [
      {
        "text": "Tutorial: Creating a Simple REST API",
        "level": 1,
        "url": "#overview"
      },
      {
        "text": "Defining the API",
        "level": 1,
        "url": "#definitions"
      },
      {
        "text": "Creating the Application",
        "level": 1,
        "url": "#implementation"
      },
      {
        "text": "Creating a Model",
        "level": 1,
        "url": "#models"
      },
      {
        "text": "Retrieving Data",
        "level": 1,
        "url": "#retrieving-data"
      },
      {
        "text": "Inserting Data",
        "level": 1,
        "url": "#inserting-data"
      },
      {
        "text": "Updating Data",
        "level": 1,
        "url": "#updating-data"
      },
      {
        "text": "Deleting Data",
        "level": 1,
        "url": "#deleting-data"
      },
      {
        "text": "Testing our Application",
        "level": 1,
        "url": "#testing"
      },
      {
        "text": "Conclusion",
        "level": 1,
        "url": "#conclusion"
      }
    ]
  },
  {
    "tutorial-vokuro": [
      {
        "text": "Tutorial: Vkur",
        "level": 1,
        "url": "#overview"
      },
      {
        "text": "Project Structure",
        "level": 1,
        "url": "#structure"
      },
      {
        "text": "Load Classes and Dependencies",
        "level": 1,
        "url": "#dependencies"
      },
      {
        "text": "Sign Up",
        "level": 1,
        "url": "#sign-up"
      }
    ]
  },
  {
    "unit-testing": [
      {
        "text": "Unit Testing",
        "level": 1,
        "url": "#overview"
      },
      {
        "text": "Integrating PHPUnit with Phalcon",
        "level": 1,
        "url": "#integration"
      },
      {
        "text": "The PHPUnit helper file",
        "level": 1,
        "url": "#unit-helper"
      },
      {
        "text": "The `phpunit.xml` file",
        "level": 1,
        "url": "#phpunit-config"
      },
      {
        "text": "Sample Unit Test",
        "level": 1,
        "url": "#sample"
      }
    ]
  },
  {
    "url": [
      {
        "text": "Generating URLs and Paths",
        "level": 1,
        "url": "#overview"
      },
      {
        "text": "Setting a base URI",
        "level": 1,
        "url": "#base-uri"
      },
      {
        "text": "Generating URIs",
        "level": 1,
        "url": "#generating-uri"
      },
      {
        "text": "Producing URLs without mod_rewrite",
        "level": 1,
        "url": "#urls-without-mod-rewrite"
      },
      {
        "text": "Producing URLs from Volt",
        "level": 1,
        "url": "#urls-from-volt"
      },
      {
        "text": "Static vs. Dynamic URIs",
        "level": 1,
        "url": "#static-vs-dynamic-uri"
      },
      {
        "text": "Implementing your own URL Generator",
        "level": 1,
        "url": "#custom-url"
      }
    ]
  },
  {
    "validation": [
      {
        "text": "Validation",
        "level": 1,
        "url": "#overview"
      },
      {
        "text": "Initializing Validation",
        "level": 1,
        "url": "#initializing"
      },
      {
        "text": "Validators",
        "level": 1,
        "url": "#validators"
      },
      {
        "text": "Callback Validator",
        "level": 1,
        "url": "#callback"
      },
      {
        "text": "Validation Messages",
        "level": 1,
        "url": "#messages"
      },
      {
        "text": "Filtering of Data",
        "level": 1,
        "url": "#filtering"
      },
      {
        "text": "Validation Events",
        "level": 1,
        "url": "#events"
      },
      {
        "text": "Cancelling Validations",
        "level": 1,
        "url": "#cancelling"
      },
      {
        "text": "Avoid validating empty values",
        "level": 1,
        "url": "empty-values"
      },
      {
        "text": "Recursive Validation",
        "level": 1,
        "url": "#recursive"
      }
    ]
  },
  {
    "views": [
      {
        "text": "Using Views",
        "level": 1,
        "url": "#overview"
      },
      {
        "text": "Integrating Views with Controllers",
        "level": 1,
        "url": "#integrating-views-with-controllers"
      },
      {
        "text": "Hierarchical Rendering",
        "level": 1,
        "url": "#hierarchical-rendering"
      },
      {
        "text": "Using Templates",
        "level": 2,
        "url": "#using-templates"
      },
      {
        "text": "Control Rendering Levels",
        "level": 2,
        "url": "#control-rendering-levels"
      },
      {
        "text": "Disabling render levels",
        "level": 2,
        "url": "#disabling-render-levels"
      },
      {
        "text": "Picking Views",
        "level": 2,
        "url": "#picking-views"
      },
      {
        "text": "Disabling the view",
        "level": 2,
        "url": "#disabling-view"
      },
      {
        "text": "Simple Rendering",
        "level": 1,
        "url": "#simple-rendering"
      },
      {
        "text": "Using Partials",
        "level": 1,
        "url": "#using-partials"
      },
      {
        "text": "Transfer values from the controller to views",
        "level": 1,
        "url": "#value-transfer"
      },
      {
        "text": "Caching View Fragments",
        "level": 1,
        "url": "#caching-fragments"
      },
      {
        "text": "Template Engines",
        "level": 1,
        "url": "#template-engines"
      },
      {
        "text": "Creating your own Template Engine Adapter",
        "level": 2,
        "url": "#custom-template-engine"
      },
      {
        "text": "Changing the Template Engine",
        "level": 2,
        "url": "#changing-template-engine"
      },
      {
        "text": "Injecting services in View",
        "level": 1,
        "url": "#injecting-services"
      },
      {
        "text": "Stand-Alone Component",
        "level": 1,
        "url": "#stand-alone"
      },
      {
        "text": "Hierarchical Rendering",
        "level": 2,
        "url": "#stand-alone-hierarchical-rendering"
      },
      {
        "text": "Simple Rendering",
        "level": 2,
        "url": "#stand-alone-simple-rendering"
      },
      {
        "text": "View Events",
        "level": 1,
        "url": "#events"
      }
    ]
  },
  {
    "volt": [
      {
        "text": "Volt: Template Engine",
        "level": 1,
        "url": "#overview"
      },
      {
        "text": "Introduction",
        "level": 1,
        "url": "#introduction"
      },
      {
        "text": "Activating Volt",
        "level": 1,
        "url": "#setup"
      },
      {
        "text": "Basic Usage",
        "level": 1,
        "url": "#basic-usage"
      },
      {
        "text": "Variables",
        "level": 1,
        "url": "#variables"
      },
      {
        "text": "Filters",
        "level": 1,
        "url": "#filters"
      },
      {
        "text": "Comments",
        "level": 1,
        "url": "#comments"
      },
      {
        "text": "List of Control Structures",
        "level": 1,
        "url": "#control-structures"
      },
      {
        "text": "For",
        "level": 2,
        "url": "#control-structures-for"
      },
      {
        "text": "Loop Controls",
        "level": 2,
        "url": "#control-structures-loops"
      },
      {
        "text": "If",
        "level": 3,
        "url": "#control-structures-if"
      },
      {
        "text": "Switch",
        "level": 3,
        "url": "#control-structures-switch"
      },
      {
        "text": "Loop Context",
        "level": 2,
        "url": "#control-structures-loop"
      },
      {
        "text": "Assignments",
        "level": 3,
        "url": "#assignments"
      },
      {
        "text": "Expressions",
        "level": 3,
        "url": "#expressions"
      },
      {
        "text": "Literals",
        "level": 2,
        "url": "#expressions-literals"
      },
      {
        "text": "Arrays",
        "level": 2,
        "url": "#expressions-arrays"
      },
      {
        "text": "Math",
        "level": 2,
        "url": "#expressions-math"
      },
      {
        "text": "Comparisons",
        "level": 2,
        "url": "#expressions-comparisons"
      },
      {
        "text": "Logic",
        "level": 2,
        "url": "#expressions-logic"
      },
      {
        "text": "Other Operators",
        "level": 2,
        "url": "#expressions-other-operators"
      },
      {
        "text": "Tests",
        "level": 1,
        "url": "#tests"
      },
      {
        "text": "Macros",
        "level": 1,
        "url": "#macros"
      },
      {
        "text": "Using Tag Helpers",
        "level": 1,
        "url": "#tag-helpers"
      },
      {
        "text": "Functions",
        "level": 1,
        "url": "#functions"
      },
      {
        "text": "View Integration",
        "level": 1,
        "url": "#view-integrations"
      },
      {
        "text": "Include",
        "level": 2,
        "url": "#view-integration-include"
      },
      {
        "text": "Partial vs Include",
        "level": 2,
        "url": "#view-integration-partial-vs-include"
      },
      {
        "text": "Template Inheritance",
        "level": 1,
        "url": "#template-inheritance"
      },
      {
        "text": "Multiple Inheritance",
        "level": 2,
        "url": "#template-inheritance-multiple"
      },
      {
        "text": "Autoescape mode",
        "level": 1,
        "url": "#autoescape"
      },
      {
        "text": "Extending Volt",
        "level": 1,
        "url": "#extending"
      },
      {
        "text": "Functions",
        "level": 2,
        "url": "#extending-functions"
      },
      {
        "text": "Filters",
        "level": 2,
        "url": "#extending-filters"
      },
      {
        "text": "Extensions",
        "level": 2,
        "url": "#extending-extensions"
      },
      {
        "text": "Caching view fragments",
        "level": 1,
        "url": "#caching-view-fragments"
      },
      {
        "text": "Inject Services into a Template",
        "level": 1,
        "url": "#services-in-templates"
      },
      {
        "text": "Stand-alone component",
        "level": 1,
        "url": "#stand-alone"
      }
    ]
  },
  {
    "webserver-wamp": [
      {
        "text": "Installation on WAMP",
        "level": 1,
        "url": "#overview"
      },
      {
        "text": "Download the right version of Phalcon",
        "level": 1,
        "url": "#phalcon"
      },
      {
        "text": "Related",
        "level": 1,
        "url": "#related"
      }
    ]
  },
  {
    "webserver-xampp": [
      {
        "text": "Installation on XAMPP",
        "level": 1,
        "url": "#overview"
      },
      {
        "text": "Download the right version of Phalcon",
        "level": 1,
        "url": "#phalcon"
      },
      {
        "text": "Screencast",
        "level": 1,
        "url": "#screencast"
      },
      {
        "text": "Related",
        "level": 1,
        "url": "#related"
      }
    ]
  }
]
