{
    "about": "私たちについて",
    "incredible_api": "Phalconベースのソリューションを開発する際にリファレンスとして使用できる素晴らしいAPIが作成されました",
    "api_documentation": "APIドキュメント",
    "blog": "ブログ",
    "community": "コミュニティ",
    "contact_us": "お問い合わせ",
    "join_forum": "あなたの探しているものが見つかりませんでしたか？ サポートフォーラムに参加して私たちにお手伝いしましょう。",
    "download": "ダウンロード",
    "explore_all_topics": "すべてのトピックを表示",
    "explore_topics": "トピックを表示",
    "facebook": "Facebook",
    "forum": "フォーラム",
    "gab": "Gab.ai",
    "general": "概要",
    "general_official_docs": "一般 - 公式Phalconドキュメント",
    "get_support": "実際の人々からのサポートを受ける",
    "github": "GitHub のプロジェクト",
    "questions_contact_us": "ご不明な点がございましたら、お問い合わせください",
    "feature_rich": "機能が豊富で、疎結合で、PHP用の高性能フルスタックフレームワーク向けに最適化されています。",
    "innovative_architecture": "その革新的なアーキテクチャはPhalconを今までに構築された最も速いPHPフレームワークにします！",
    "looking_for_help": "ヘルプをお探しですか？コミュニティに参加する",
    "meet_incubator": "Incubatorに出会う",
    "official_forums": "公式フォーラム",
    "official_docs": "公式Phalconドキュメント",
    "incubator_amazing_features": "私たちのコミュニティは、Incubatorを介してPhalconのための素晴らしい機能を日々開発しています。",
    "resources": "リソース",
    "sponsors": "スポンサー",
    "support_forums": "サポートフォーラム",
    "support_us": "サポートする",
    "twitter": "Twitter",
    "unlike_traditional_frameworks": "従来のフレームワークと異なり、PhalconはC拡張として書かれ、ハイパフォーマンス向けに最適化されています。",
    "version": "バージョン",
    "we_did_our_Best": "この製品に関連するすべてのトピックを網羅しています。 各セクションには、各カテゴリのトピック数を表す数字があります。",
    "what_is_phalcon": "Phalconとは",
    "when_you_are_stuck": "何かにつまづいた時は、私たちはあなたを助けるためにここにいる事を思い出してください。",
    "write_to_us_now": "いますぐ私たちに知れせてください",
    "oops": "おっと！ 間違った住所などを入力したようです。 いずれにせよ、私たちに知らせてください",
    "back_to_main_page": "メインページに戻る",
    "the_phalcon_team": "Phalcon チーム",
    "edit_on_github": "GitHub上で編集",
    "edit_on_crowdin": "Crowdinで編集",
    "license": "ライセンス",
    "development": "Development by",
    "apologize": "ご迷惑をおかけして申し訳ありません。 現時点では何かが正しくないようです。 我々はまもなくそれを解決するでしょう。 必要な場合は、いつでもお問い合わせください",
    "check_back_later": "数分で確認してください！"
}
